namedentities/__init__.py
namedentities/core.py
namedentities/version.py
namedentities-1.9.4.dist-info/DESCRIPTION.rst
namedentities-1.9.4.dist-info/METADATA
namedentities-1.9.4.dist-info/RECORD
namedentities-1.9.4.dist-info/WHEEL
namedentities-1.9.4.dist-info/metadata.json
namedentities-1.9.4.dist-info/top_level.txt
